wrap/__init__.py
wrap/_wrap_py_launcher.py
wrap/w1.py
MVSCoursePythonKids_ru-0.1.0.1.dist-info/METADATA
MVSCoursePythonKids_ru-0.1.0.1.dist-info/WHEEL
MVSCoursePythonKids_ru-0.1.0.1.dist-info/top_level.txt
MVSCoursePythonKids_ru-0.1.0.1.dist-info/RECORD
