Metadata-Version: 2.1
Name: MVSCoursePythonKids-ru
Version: 0.1.0.1
Summary: UNKNOWN
Home-page: UNKNOWN
Author: UNKNOWN
Author-email: UNKNOWN
License: UNKNOWN
Platform: UNKNOWN
Requires-Dist: wrap-py (==0.2.*,>=0.2.2.1)
Requires-Dist: wrap-data-source (==0.1.*,>=0.1.0)
Requires-Dist: wds-files-general (==0.1.*,>=0.1.2)
Requires-Dist: wrap-mENdRU (==0.1.*,>=0.1.1.1)
